{
    "fluentMethods": true,
    "relationships": [
        {
            "relationshipName": "facturier",
            "otherEntityName": "facturier",
            "relationshipType": "many-to-one",
            "otherEntityField": "id"
        }
    ],
    "fields": [
        {
            "fieldName": "numero",
            "fieldType": "String"
        },
        {
            "fieldName": "type",
            "fieldType": "String"
        },
        {
            "fieldName": "date",
            "fieldType": "LocalDate"
        },
        {
            "fieldName": "montant",
            "fieldType": "Long"
        },
        {
            "fieldName": "regler",
            "fieldType": "Regle",
            "fieldValues": "OUI,NON"
        }
    ],
    "changelogDate": "20180215080231",
    "entityTableName": "facture",
    "dto": "no",
    "pagination": "no",
    "service": "no",
    "jpaMetamodelFiltering": false,
    "angularJSSuffix": "mySuffix"
}